swak/__init__.py
swak/cli/__init__.py
swak/cli/argparser.py
swak/cli/envparser.py
swak/cli/exceptions.py
swak/cli/importer.py
swak/cloud/__init__.py
swak/cloud/aws/__init__.py
swak/cloud/aws/bucket.py
swak/cloud/aws/clients.py
swak/cloud/aws/df2s3.py
swak/cloud/aws/discovery.py
swak/cloud/aws/exceptions.py
swak/cloud/aws/s32df.py
swak/cloud/aws/s32local.py
swak/cloud/gcp/__init__.py
swak/cloud/gcp/bucket.py
swak/cloud/gcp/clients.py
swak/cloud/gcp/dataset.py
swak/cloud/gcp/df2gbq.py
swak/cloud/gcp/exceptions.py
swak/cloud/gcp/gcs2df.py
swak/cloud/gcp/gcs2local.py
swak/cloud/gcp/query.py
swak/cloud/gcp/query2df.py
swak/cloud/gcp/query2gcs.py
swak/dictionary/__init__.py
swak/dictionary/valuesgetter.py
swak/funcflow/__init__.py
swak/funcflow/curry.py
swak/funcflow/exceptions.py
swak/funcflow/fallback.py
swak/funcflow/filter.py
swak/funcflow/fork.py
swak/funcflow/map.py
swak/funcflow/misc.py
swak/funcflow/partial.py
swak/funcflow/pipe.py
swak/funcflow/reduce.py
swak/funcflow/route.py
swak/funcflow/safe.py
swak/funcflow/split.py
swak/funcflow/sum.py
swak/funcflow/concurrent/__init__.py
swak/funcflow/concurrent/processfork.py
swak/funcflow/concurrent/processmap.py
swak/funcflow/concurrent/threadfork.py
swak/funcflow/concurrent/threadmap.py
swak/funcflow/loggers/__init__.py
swak/funcflow/loggers/file.py
swak/funcflow/loggers/formats.py
swak/funcflow/loggers/json.py
swak/funcflow/loggers/std.py
swak/jsonobject/__init__.py
swak/jsonobject/exceptions.py
swak/jsonobject/jsonobject.py
swak/jsonobject/jsonobjects.py
swak/jsonobject/fields/__init__.py
swak/jsonobject/fields/custom.py
swak/jsonobject/fields/flexidate.py
swak/jsonobject/fields/flexitime.py
swak/jsonobject/fields/maybe.py
swak/jsonobject/fields/normalizers.py
swak/jsonobject/fields/resolve.py
swak/misc/__init__.py
swak/misc/enums.py
swak/misc/repr.py
swak/misc/loggers/__init__.py
swak/misc/loggers/file.py
swak/misc/loggers/formats.py
swak/misc/loggers/json.py
swak/misc/loggers/std.py
swak/pd/__init__.py
swak-0.5.6.dist-info/licenses/LICENSE
swak-0.5.6.dist-info/METADATA
swak-0.5.6.dist-info/WHEEL
swak-0.5.6.dist-info/top_level.txt
swak-0.5.6.dist-info/RECORD
